{
  "display": "Takumi, Empty Vessel",
  "name": "Takumi",
  "title": "Empty Vessel",
  "id": "takumi-empty-vessel",
  "color": "Colorless",
  "weapon_type": "Bow",
  "link": "https://kagerochart.com/hero/takumi-empty-vessel",
  "move_type": "Infantry",
  "LowestRarity": 3,
  "weapon": [
    "skadi",
    "silver-bow",
    "steel-bow",
    "iron-bow"
  ],
  "special": [
    "vengeance",
    "retribution"
  ],
  "passive_a": [
    "fury-3",
    "fury-2",
    "fury-1"
  ],
  "passive_c": [
    "spd-smoke-3",
    "spd-smoke-2",
    "spd-smoke-1"
  ],
  "base_stat": {
    "star_5": {
      "hp": 15,
      "atk": 9,
      "spd": 10,
      "def": 6,
      "res": 5
    },
    "growth": {
      "hp": 50,
      "atk": 50,
      "spd": 55,
      "def": 45,
      "res": 45,
      "total": 245
    },
    "growth_type": 66
  }
}